{
  "total_companies": 6006,
  "last_updated": "2026-04-02T16:55:45.761829Z",
  "by_confidence": {
    "5": 58,
    "4": 4579,
    "3": 1343,
    "1": 26
  },
  "top_countries": {
    "DK": 2204,
    "SE": 883,
    "DE": 505,
    "US": 286,
    "NO": 240,
    "NL": 193,
    "BE": 141,
    "IN": 134,
    "IT": 131,
    "FR": 130,
    "PL": 129,
    "XX": 124,
    "FI": 119,
    "ES": 100,
    "UK": 98,
    "GB": 83,
    "ZA": 56,
    "BR": 55,
    "CA": 42,
    "SA": 37
  },
  "top_sources": {
    "global_jobs": 4233,
    "TheirStack": 178,
    "web_search": 164,
    "theirstack": 162,
    "bulk_search": 123,
    "theirstack_nordic_batch1": 69,
    "theirstack_asia_batch2": 51,
    "theirstack_africa_batch1": 50,
    "theirstack_expansion_batch2": 50,
    "theirstack_germany_batch1": 50
  },
  "date_range": {
    "first": "2026-03-20T18:08:51.494734Z",
    "latest": "2026-04-02T16:52:10.534433Z"
  }
}